say_message/__init__.py
say_message/say_message.py
tests/__init__.py
tests/test_say_message.py
say_message-0.0.4.dist-info/LICENSE
say_message-0.0.4.dist-info/METADATA
say_message-0.0.4.dist-info/WHEEL
say_message-0.0.4.dist-info/top_level.txt
say_message-0.0.4.dist-info/RECORD
