Metadata-Version: 2.1
Name: say-message
Version: 0.0.4
Summary: A library that print a message.
Home-page: https://github.com/eocode/First-Python-Package
Author: Elias Ojeda Medina
Author-email: hola@eliasojedamedina.com
License: UNKNOWN
Project-URL: Homepage, https://github.com/eocode/First-Python-Package
Project-URL: Issue tracker, https://github.com/eocode/First-Python-Package/issues
Project-URL: Code, https://github.com/eocode/First-Python-Package
Project-URL: Documentation, https://github.com/eocode/First-Python-Package/wiki
Platform: UNKNOWN
Classifier: Programming Language :: Python :: 3
Classifier: License :: OSI Approved :: MIT License
Classifier: Operating System :: OS Independent
Requires-Python: >=3.6
